{"widgetBindings": [
    {
        "propertyName": "value",
        "serverBindName": "g_ModemData.carrierFreq",
        "widgetId": "dial",
        "options": {"dataType": "Double"}
    },
    {
        "propertyName": "series_0_Values",
        "serverBindName": "g_ModemData.OutputBuffer",
        "widgetId": "graph",
        "options": {"dataType": "array"}
    },
    {
        "propertyName": "checked",
        "serverBindName": "g_ModemData.stop",
        "widgetId": "toggle",
        "options": {"dataType": "boolean"}
    }
]}